beeai_server/__init__.py
beeai_server/application.py
beeai_server/bootstrap.py
beeai_server/configuration.py
beeai_server/exceptions.py
beeai_server/logging_config.py
beeai_server/telemetry.py
beeai_server/api/__init__.py
beeai_server/api/auth.py
beeai_server/api/dependencies.py
beeai_server/api/routes/__init__.py
beeai_server/api/routes/acp.py
beeai_server/api/routes/env.py
beeai_server/api/routes/files.py
beeai_server/api/routes/llm.py
beeai_server/api/routes/provider.py
beeai_server/api/routes/ui.py
beeai_server/api/schema/__init__.py
beeai_server/api/schema/acp.py
beeai_server/api/schema/common.py
beeai_server/api/schema/env.py
beeai_server/api/schema/files.py
beeai_server/api/schema/provider.py
beeai_server/crons/__init__.py
beeai_server/crons/auto_remove_providers.py
beeai_server/crons/cleanup_old_requests.py
beeai_server/crons/scale_down_providers.py
beeai_server/crons/sync_registry_providers.py
beeai_server/domain/__init__.py
beeai_server/domain/constants.py
beeai_server/domain/models/__init__.py
beeai_server/domain/models/agent.py
beeai_server/domain/models/file.py
beeai_server/domain/models/provider.py
beeai_server/domain/models/registry.py
beeai_server/domain/models/user.py
beeai_server/domain/repositories/__init__.py
beeai_server/domain/repositories/agent.py
beeai_server/domain/repositories/env.py
beeai_server/domain/repositories/files.py
beeai_server/domain/repositories/provider.py
beeai_server/domain/repositories/users.py
beeai_server/infrastructure/__init__.py
beeai_server/infrastructure/kubernetes/__init__.py
beeai_server/infrastructure/kubernetes/provider_deployment_manager.py
beeai_server/infrastructure/object_storage/__init__.py
beeai_server/infrastructure/object_storage/create_buckets.py
beeai_server/infrastructure/object_storage/repository.py
beeai_server/infrastructure/persistence/__init__.py
beeai_server/infrastructure/persistence/unit_of_work.py
beeai_server/infrastructure/persistence/migrations/__init__.py
beeai_server-0.2.8.dist-info/METADATA
beeai_server-0.2.8.dist-info/WHEEL
beeai_server-0.2.8.dist-info/entry_points.txt
beeai_server-0.2.8.dist-info/RECORD
