Metadata-Version: 2.4
Name: beeai-server
Version: 0.2.8
Summary: BeeAI server
Author: IBM Corp.
Requires-Python: <4.0,>=3.11
Requires-Dist: acp-sdk>=0.10.1
Requires-Dist: aioboto3>=14.3.0
Requires-Dist: aiodocker>=0.24.0
Requires-Dist: aiohttp>=3.11.11
Requires-Dist: alembic>=1.15.2
Requires-Dist: anyio>=4.9.0
Requires-Dist: asgiref>=3.8.1
Requires-Dist: asyncpg>=0.30.0
Requires-Dist: beeai-framework>=0.1.20
Requires-Dist: cachetools>=5.5.2
Requires-Dist: fastapi[standard]>=0.115.7
Requires-Dist: httpx>=0.28.1
Requires-Dist: kink>=0.8.1
Requires-Dist: kr8s>=0.20.7
Requires-Dist: opentelemetry-api>=1.30.0
Requires-Dist: opentelemetry-exporter-otlp-proto-http>=1.30.0
Requires-Dist: opentelemetry-sdk>=1.30.0
Requires-Dist: orjson>=3.10.15
Requires-Dist: pydantic-settings>=2.7.1
Requires-Dist: pydantic>=2.10.6
Requires-Dist: pyjwt>=2.10.1
Requires-Dist: python-multipart>=0.0.20
Requires-Dist: sqlalchemy[asyncio]>=2.0.41
Requires-Dist: structlog>=25.1.0
Requires-Dist: tenacity>=9.0.0
Requires-Dist: uvicorn>=0.34.0
